README.rst
setup.py
simpledbf/__init__.py
simpledbf/simpledbf.py
simpledbf.egg-info/PKG-INFO
simpledbf.egg-info/SOURCES.txt
simpledbf.egg-info/dependency_links.txt
simpledbf.egg-info/top_level.txt