Metadata-Version: 1.1
Name: simpledbf
Version: 0.2.4
Summary: Convert DBF files to CSV, DataFrames, HDF5 tables, and SQL tables. Python3 compatible.
Home-page: https://github.com/rnelsonchem/simpledbf
Author: Ryan Nelson
Author-email: rnelsonchem@gmail.com
License: BSD
Keywords: DBF CSV Pandas SQLalchemy PyTables DataFrame SQL HDF
Platform: UNKNOWN
Classifier: Development Status :: 4 - Beta
Classifier: Intended Audience :: Developers
Classifier: Intended Audience :: Science/Research
Classifier: License :: OSI Approved :: BSD License
Classifier: Programming Language :: Python :: 2
Classifier: Programming Language :: Python :: 2.7
Classifier: Programming Language :: Python :: 3
Classifier: Programming Language :: Python :: 3.4
